data/__init__.py
data/gai.yml
data/version.txt
data/data/docker-compose.yml
data/data/gai/agents/Diana/Diana.json
data/data/gai/agents/Diana/images/128x128.png
data/data/gai/agents/Diana/images/256x256.png
data/data/gai/agents/Diana/images/512x512.png
data/data/gai/agents/Diana/images/64x64.png
data/data/gai/agents/Diana/images/image.json
data/data/gai/agents/George/George.json
data/data/gai/agents/George/images/128x128.png
data/data/gai/agents/George/images/256x256.png
data/data/gai/agents/George/images/512x512.png
data/data/gai/agents/George/images/64x64.png
data/data/gai/agents/George/images/image.json
data/data/gai/agents/Sara/Sara.json
data/data/gai/agents/Sara/images/128x128.png
data/data/gai/agents/Sara/images/256x256.png
data/data/gai/agents/Sara/images/512x512.png
data/data/gai/agents/Sara/images/64x64.png
data/data/gai/agents/Sara/images/image.json
data/data/gai/images/female.jpg
data/data/gai/images/male.jpg
data/data/gai/project-templates/minimal/.gitignore
data/data/gai/project-templates/minimal/.python-version
data/data/gai/project-templates/minimal/LICENSE
data/data/gai/project-templates/minimal/Makefile
data/data/gai/project-templates/minimal/pyproject.toml
data/data/gai/project-templates/minimal/.devcontainer/Dockerfile.devcontainer
data/data/gai/project-templates/minimal/.devcontainer/devcontainer.json
data/data/gai/project-templates/minimal/.devcontainer/docker-compose.override.yml
data/data/gai/project-templates/minimal/.devcontainer/docker-compose.yml
data/data/gai/project-templates/minimal/.devcontainer/postStartCommand.sh
data/data/gai/project-templates/tool/.gitignore
data/data/gai/project-templates/tool/LICENSE
data/data/gai/project-templates/tool/Makefile
data/data/gai/project-templates/tool/README.md
data/data/gai/project-templates/tool/pyproject.toml
data/data/gai/project-templates/tool/.devcontainer/Dockerfile.devcontainer
data/data/gai/project-templates/tool/.devcontainer/devcontainer.json
gai_init-0.1.34.dist-info/METADATA
gai_init-0.1.34.dist-info/WHEEL
gai_init-0.1.34.dist-info/entry_points.txt
gai_init-0.1.34.dist-info/RECORD
